blazar_tempest_plugin/README.rst
blazar_tempest_plugin/__init__.py
blazar_tempest_plugin/config.py
blazar_tempest_plugin/plugin.py
blazar_tempest_plugin/services/__init__.py
blazar_tempest_plugin/services/reservation/__init__.py
blazar_tempest_plugin/services/reservation/reservation_client.py
blazar_tempest_plugin/tests/__init__.py
blazar_tempest_plugin/tests/api/__init__.py
blazar_tempest_plugin/tests/api/fixtures.py
blazar_tempest_plugin/tests/api/test_blazar_api.py
blazar_tempest_plugin/tests/api/gabbits/allocations.yaml
blazar_tempest_plugin/tests/api/gabbits/hosts.yaml
blazar_tempest_plugin/tests/api/gabbits/leases.yaml
blazar_tempest_plugin/tests/scenario/__init__.py
blazar_tempest_plugin/tests/scenario/manager_freeze.py
blazar_tempest_plugin/tests/scenario/resource_reservation_scenario.py
blazar_tempest_plugin/tests/scenario/test_flavor_reservation.py
blazar_tempest_plugin/tests/scenario/test_host_reservation.py
blazar_tempest_plugin/tests/scenario/test_instance_reservation.py
blazar_tempest_plugin/tests/scenario/test_reservation_concurrency.py
blazar_tempest_plugin-0.17.0.dist-info/AUTHORS
blazar_tempest_plugin-0.17.0.dist-info/LICENSE
blazar_tempest_plugin-0.17.0.dist-info/METADATA
blazar_tempest_plugin-0.17.0.dist-info/WHEEL
blazar_tempest_plugin-0.17.0.dist-info/entry_points.txt
blazar_tempest_plugin-0.17.0.dist-info/pbr.json
blazar_tempest_plugin-0.17.0.dist-info/top_level.txt
blazar_tempest_plugin-0.17.0.dist-info/RECORD
