Metadata-Version: 2.1
Name: blazar_tempest_plugin
Version: 0.17.0
Summary: Tempest plugin for Blazar Project
Home-page: https://docs.openstack.org/blazar/latest/
Author: OpenStack
Author-email: openstack-discuss@lists.openstack.org
Classifier: Environment :: OpenStack
Classifier: Intended Audience :: Information Technology
Classifier: Intended Audience :: System Administrators
Classifier: License :: OSI Approved :: Apache Software License
Classifier: Operating System :: POSIX :: Linux
Classifier: Programming Language :: Python
Classifier: Programming Language :: Python :: 3
Classifier: Programming Language :: Python :: 3.9
Classifier: Programming Language :: Python :: 3.10
Classifier: Programming Language :: Python :: 3.11
Classifier: Programming Language :: Python :: 3.12
License-File: LICENSE
License-File: AUTHORS
Requires-Dist: pbr !=2.1.0,>=2.0.0
Requires-Dist: oslo.config >=5.2.0
Requires-Dist: oslo.log >=3.36.0
Requires-Dist: oslo.serialization !=2.19.1,>=2.18.0
Requires-Dist: oslo.utils >=3.37.0
Requires-Dist: tempest >=27.0.0
Requires-Dist: gabbi >=1.42.1
